power01_cmd/__init__.py
power01_cmd/cmd.py
power01_cmd-0.2.0.dist-info/METADATA
power01_cmd-0.2.0.dist-info/WHEEL
power01_cmd-0.2.0.dist-info/entry_points.txt
power01_cmd-0.2.0.dist-info/top_level.txt
power01_cmd-0.2.0.dist-info/RECORD
