Metadata-Version: 2.1
Name: power01_cmd
Version: 0.2.0
Summary: Default template for PDM package
Author-email: sooj1n <sujin19371@gmail.com>
License: MIT
Project-URL: Homepage, https://github.com/sooj1n/power01_cmd
Project-URL: Issues, https://github.com/sooj1n/power01_cmd/issues
Requires-Python: >=3.9
Requires-Dist: power01-div >=0.1.0
Requires-Dist: power01-mul >=0.1.0
Requires-Dist: power01-plus >=0.1.0
Requires-Dist: power01-min >=0.1.1
